pretty2d/__init__.py
pretty2d/border.py
pretty2d/formatter.py
pretty2d-1.3.dist-info/licenses/LICENSE
pretty2d-1.3.dist-info/METADATA
pretty2d-1.3.dist-info/WHEEL
pretty2d-1.3.dist-info/top_level.txt
pretty2d-1.3.dist-info/RECORD
