Metadata-Version: 2.4
Name: Pretty2D
Version: 1.3
Summary: A lightweight library for pretty-printing 2D tabular data with customizable borders.
Author: Ali Ahmad
License: MIT License
Project-URL: Homepage, https://github.com/Absolute 16/Pretty2D
Project-URL: Documentation, https://github.com/Absolute/Pretty2D#readme
Project-URL: Source, https://github.com/Absolute16/Pretty2D
Project-URL: Issues, https://github.com/Absolute16/Pretty2D/issues
Keywords: table,pretty print,2d,formatting,cli,ascii-table
Classifier: Programming Language :: Python :: 3
Classifier: License :: OSI Approved :: MIT License
Classifier: Operating System :: OS Independent
Requires-Python: >=3.8
License-File: LICENSE
Dynamic: license-file
